{"nodes": [{"size": 1.0, "y": 0.0, "name": "EASYCONNECTISP-AS-AP Easy Connect- ISP", "country_code": "AF", "x": 0.0, "color": "#0055ff", "country": "\u963f\u5bcc\u6c57", "_id": "133894", "id": "133894", "label": "133894"}, {"size": 0.6761094622291788, "y": -1.58651747952706, "name": "ETISALATAFG-AS-AP Etisalat Afghan", "country_code": "AF", "x": 0.3249450701147791, "color": "#0088ff", "country": "\u963f\u5bcc\u6c57", "_id": "131284", "id": "131284", "label": "131284"}, {"size": 0.48664564329483906, "y": 0.16408496512257528, "name": "MTNAFGHANISTAN-AS-AP MTNAFGHANISTAN", "country_code": "AF", "x": -2.561521718222386, "color": "#00aaff", "country": "\u963f\u5bcc\u6c57", "_id": "132471", "id": "132471", "label": "132471"}, {"size": 0.35221892445835756, "y": -1.169938589054226, "name": "ANS-AS-AP Ariana Network Services Co", "country_code": "AF", "x": 3.0202237903157085, "color": "#33bbff", "country": "\u963f\u5bcc\u6c57", "_id": "133066", "id": "133066", "label": "133066"}, {"size": 0.24794946068175394, "y": 1.112781811056417, "name": "GCN-DCN-AS AFGHANTELECOM GOVERNMENT COMMUNICATION NETWORK", "country_code": "AF", "x": 3.5918264132894313, "color": "#33bbff", "country": "\u963f\u5bcc\u6c57", "_id": "55330", "id": "55330", "label": "55330"}, {"size": 0, "y": -4.330127018922192, "name": "THREESPARK-NET-AF G/38 Qala e Mosa Shaheed Square", "country_code": "AF", "x": -2.500000000000002, "color": "#99ddff", "country": "\u963f\u5bcc\u6c57", "_id": "58697", "id": "58697", "label": "58697"}, {"size": 0, "y": 0.0, "name": "NORTHTELECOM-AF North Telecom", "country_code": "AF", "x": 5.0, "color": "#99ddff", "country": "\u963f\u5bcc\u6c57", "_id": "134134", "id": "134134", "label": "134134"}, {"size": 0, "y": 4.330127018922194, "name": "STANNET-AS-AP STAN Telecom", "country_code": "AF", "x": -2.499999999999999, "color": "#99ddff", "country": "\u963f\u5bcc\u6c57", "_id": "64081", "id": "64081", "label": "64081"}], "edges": [{"target": "133894", "color": "#0055ff", "source": "133894", "transmit": 945, "id": "0", "size": 0}, {"target": "131284", "color": "#0088ff", "source": "131284", "transmit": 460, "id": "1", "size": 0}, {"target": "134134", "color": "#0088ff", "source": "132471", "transmit": 139, "id": "2", "size": 0}, {"target": "58697", "color": "#00aaff", "source": "133066", "transmit": 134, "id": "3", "size": 0}, {"target": "64081", "color": "#33bbff", "source": "55330", "transmit": 76, "id": "4", "size": 0}, {"target": "134134", "color": "#33bbff", "source": "131284", "transmit": 74, "id": "5", "size": 0}, {"target": "133894", "color": "#66ccff", "source": "131284", "transmit": 63, "id": "6", "size": 0}]}