{"nodes": [{"size": 1.0, "y": 0.0, "name": "HOTNET-IL AMS-IX Admin LAN", "country_code": "IL", "x": -0.0, "color": "#0055ff", "country": "\u4ee5\u8272\u5217", "_id": "12849", "id": "12849", "label": "12849"}, {"size": 0.7757561757824246, "y": 1.0584976804157662, "name": "TRIPLEC-ASN", "country_code": "IL", "x": -0.36974988579783785, "color": "#0088ff", "country": "\u4ee5\u8272\u5217", "_id": "50463", "id": "50463", "label": "50463"}, {"size": 0.6445819475968362, "y": -0.06924505372804297, "name": "BEZEQ-INTERNATIONAL-AS Bezeqint Internet Backbone", "country_code": "IL", "x": -1.7757406685340211, "color": "#0088ff", "country": "\u4ee5\u8272\u5217", "_id": "8551", "id": "8551", "label": "8551"}, {"size": 0.5515123515648492, "y": 0.4352714636307919, "name": "GOLDENLINES-ASN 012 Smile Communications Main Autonomous System", "country_code": "IL", "x": -2.199788176829986, "color": "#00aaff", "country": "\u4ee5\u8272\u5217", "_id": "9116", "id": "9116", "label": "9116"}, {"size": 0.4793219644442286, "y": -2.2886355161543315, "name": "NV-ASN 013 NetVision Ltd.", "country_code": "IL", "x": -1.2408819008884067, "color": "#00aaff", "country": "\u4ee5\u8272\u5217", "_id": "1680", "id": "1680", "label": "1680"}, {"size": 0.4203381233792609, "y": 2.0828104076750544, "name": "RIMON1", "country_code": "IL", "x": 2.0154647319830232, "color": "#00aaff", "country": "\u4ee5\u8272\u5217", "_id": "42925", "id": "42925", "label": "42925"}, {"size": 0.3704679963417695, "y": 3.1199436655223254, "name": "PARTNER-AS", "country_code": "IL", "x": 0.4167914523065167, "color": "#33bbff", "country": "\u4ee5\u8272\u5217", "_id": "12400", "id": "12400", "label": "12400"}, {"size": 0.32726852734727374, "y": 1.6759112722644154, "name": "INTERNET_BINAT", "country_code": "IL", "x": -2.9164211398449837, "color": "#33bbff", "country": "\u4ee5\u8272\u5217", "_id": "25003", "id": "25003", "label": "25003"}, {"size": 0.28916389519367247, "y": 1.5101884090843891, "name": "MIRS-AS", "country_code": "IL", "x": 3.217379394238884, "color": "#33bbff", "country": "\u4ee5\u8272\u5217", "_id": "21450", "id": "21450", "label": "21450"}, {"size": 0.255078140226653, "y": -2.3883316615097647, "name": "HILAT_NETWORKS", "country_code": "IL", "x": -2.858073880051836, "color": "#33bbff", "country": "\u4ee5\u8272\u5217", "_id": "199270", "id": "199270", "label": "199270"}, {"size": 0.2242438242175755, "y": -0.7309320101543083, "name": "", "country_code": "IL", "x": 3.809288582287522, "color": "#33bbff", "country": "\u4ee5\u8272\u5217", "_id": "16116", "id": "16116", "label": "16116"}, {"size": 0.19609429916168541, "y": -1.9304472527246954, "name": "XFONE", "country_code": "IL", "x": -3.5256180735377765, "color": "#66ccff", "country": "\u4ee5\u8272\u5217", "_id": "47956", "id": "47956", "label": "47956"}, {"size": 0.17019924631743455, "y": -0.9450694047094155, "name": "IL-GOLANTELECOM", "country_code": "IL", "x": -4.0399351592056565, "color": "#66ccff", "country": "\u4ee5\u8272\u5217", "_id": "198484", "id": "198484", "label": "198484"}, {"size": 0.14622417212419414, "y": 4.268459877539597, "name": "IIX-ASN", "country_code": "IL", "x": 0.059827923748751594, "color": "#66ccff", "country": "\u4ee5\u8272\u5217", "_id": "5585", "id": "5585", "label": "5585"}, {"size": 0, "y": -2.4999999999999987, "name": "IL-3SAMNET-AS", "country_code": "IL", "x": -4.3301270189221945, "color": "#99ddff", "country": "\u4ee5\u8272\u5217", "_id": "200742", "id": "200742", "label": "200742"}, {"size": 0, "y": -3.5355339059327355, "name": "CLOUDWEBMANAGE-", "country_code": "IL", "x": -3.5355339059327395, "color": "#99ddff", "country": "\u4ee5\u8272\u5217", "_id": "44709", "id": "44709", "label": "44709"}, {"size": 0, "y": -4.330127018922192, "name": "NETSTYLE2", "country_code": "IL", "x": -2.500000000000002, "color": "#99ddff", "country": "\u4ee5\u8272\u5217", "_id": "58018", "id": "58018", "label": "58018"}, {"size": 0, "y": -4.829629131445341, "name": "NETSTYLE2", "country_code": "IL", "x": -1.2940952255126077, "color": "#99ddff", "country": "\u4ee5\u8272\u5217", "_id": "43945", "id": "43945", "label": "43945"}, {"size": 0, "y": -5.0, "name": "BEZEK", "country_code": "IL", "x": -9.184850993605148e-16, "color": "#99ddff", "country": "\u4ee5\u8272\u5217", "_id": "6810", "id": "6810", "label": "6810"}, {"size": 0, "y": -4.829629131445342, "name": "INTERHOST", "country_code": "IL", "x": 1.2940952255126015, "color": "#99ddff", "country": "\u4ee5\u8272\u5217", "_id": "61102", "id": "61102", "label": "61102"}, {"size": 0, "y": -4.330127018922195, "name": "HQserv Communication Solutions", "country_code": "IL", "x": 2.4999999999999964, "color": "#99ddff", "country": "\u4ee5\u8272\u5217", "_id": "42994", "id": "42994", "label": "42994"}, {"size": 0, "y": -3.5355339059327386, "name": "IBC-AS", "country_code": "IL", "x": 3.535533905932737, "color": "#99ddff", "country": "\u4ee5\u8272\u5217", "_id": "21145", "id": "21145", "label": "21145"}, {"size": 0, "y": -2.500000000000002, "name": "TELZAR-ASN", "country_code": "IL", "x": 4.330127018922192, "color": "#99ddff", "country": "\u4ee5\u8272\u5217", "_id": "51825", "id": "51825", "label": "51825"}, {"size": 0, "y": -1.294095225512608, "name": "TEHILA-AS", "country_code": "IL", "x": 4.829629131445341, "color": "#99ddff", "country": "\u4ee5\u8272\u5217", "_id": "8867", "id": "8867", "label": "8867"}, {"size": 0, "y": 0.0, "name": "ITCNG ITC NG BGP AS number", "country_code": "IL", "x": 5.0, "color": "#99ddff", "country": "\u4ee5\u8272\u5217", "_id": "202940", "id": "202940", "label": "202940"}, {"size": 0, "y": 1.2940952255126037, "name": "OMC-EU", "country_code": "IL", "x": 4.8296291314453415, "color": "#99ddff", "country": "\u4ee5\u8272\u5217", "_id": "56378", "id": "56378", "label": "56378"}, {"size": 0, "y": 2.4999999999999996, "name": "RADWARE-AS", "country_code": "IL", "x": 4.330127018922194, "color": "#99ddff", "country": "\u4ee5\u8272\u5217", "_id": "15823", "id": "15823", "label": "15823"}, {"size": 0, "y": 3.5355339059327373, "name": "NEWAY-ASN", "country_code": "IL", "x": 3.5355339059327378, "color": "#99ddff", "country": "\u4ee5\u8272\u5217", "_id": "206056", "id": "206056", "label": "206056"}, {"size": 0, "y": 4.330127018922193, "name": "NET-STYLE-DEVELOPMENT-LTD", "country_code": "IL", "x": 2.5000000000000004, "color": "#99ddff", "country": "\u4ee5\u8272\u5217", "_id": "199267", "id": "199267", "label": "199267"}, {"size": 0, "y": 4.829629131445341, "name": "ISOC-IL-AS", "country_code": "IL", "x": 1.2940952255126048, "color": "#99ddff", "country": "\u4ee5\u8272\u5217", "_id": "31391", "id": "31391", "label": "31391"}, {"size": 0, "y": 5.0, "name": "TELIT-AS", "country_code": "IL", "x": 3.061616997868383e-16, "color": "#99ddff", "country": "\u4ee5\u8272\u5217", "_id": "201093", "id": "201093", "label": "201093"}, {"size": 0, "y": 4.8296291314453415, "name": "CHECKPOINT", "country_code": "IL", "x": -1.2940952255126033, "color": "#99ddff", "country": "\u4ee5\u8272\u5217", "_id": "25046", "id": "25046", "label": "25046"}, {"size": 0, "y": 4.330127018922194, "name": "XGLOBE-199391", "country_code": "IL", "x": -2.499999999999999, "color": "#99ddff", "country": "\u4ee5\u8272\u5217", "_id": "199391", "id": "199391", "label": "199391"}, {"size": 0, "y": 3.5355339059327378, "name": "EMIT", "country_code": "IL", "x": -3.5355339059327373, "color": "#99ddff", "country": "\u4ee5\u8272\u5217", "_id": "35435", "id": "35435", "label": "35435"}, {"size": 0, "y": 2.5000000000000018, "name": "TABOOLA-AS", "country_code": "IL", "x": -4.330127018922193, "color": "#99ddff", "country": "\u4ee5\u8272\u5217", "_id": "200478", "id": "200478", "label": "200478"}, {"size": 0, "y": 1.294095225512605, "name": "ANNATEL", "country_code": "IL", "x": -4.829629131445341, "color": "#99ddff", "country": "\u4ee5\u8272\u5217", "_id": "204814", "id": "204814", "label": "204814"}, {"size": 0, "y": 6.123233995736766e-16, "name": "LAN-WAN-", "country_code": "IL", "x": -5.0, "color": "#99ddff", "country": "\u4ee5\u8272\u5217", "_id": "12517", "id": "12517", "label": "12517"}, {"size": 0, "y": -1.2940952255126017, "name": "TABOOLA-O", "country_code": "IL", "x": -4.829629131445342, "color": "#99ddff", "country": "\u4ee5\u8272\u5217", "_id": "206614", "id": "206614", "label": "206614"}], "edges": [{"target": "12849", "color": "#0055ff", "source": "12849", "transmit": 13964, "id": "0", "size": 0}, {"target": "21450", "color": "#0055ff", "source": "12849", "transmit": 4650, "id": "1", "size": 0}, {"target": "50463", "color": "#0055ff", "source": "50463", "transmit": 2607, "id": "2", "size": 0}, {"target": "12400", "color": "#0055ff", "source": "9116", "transmit": 937, "id": "3", "size": 0}, {"target": "16116", "color": "#0055ff", "source": "8551", "transmit": 806, "id": "4", "size": 0}, {"target": "42925", "color": "#0055ff", "source": "42925", "transmit": 592, "id": "5", "size": 0}, {"target": "50463", "color": "#0055ff", "source": "1680", "transmit": 306, "id": "6", "size": 0}, {"target": "25003", "color": "#0055ff", "source": "25003", "transmit": 138, "id": "7", "size": 0}, {"target": "51825", "color": "#0055ff", "source": "8551", "transmit": 129, "id": "8", "size": 0}, {"target": "31391", "color": "#0088ff", "source": "50463", "transmit": 129, "id": "9", "size": 0}, {"target": "198484", "color": "#0088ff", "source": "12849", "transmit": 126, "id": "10", "size": 0}, {"target": "199391", "color": "#0088ff", "source": "8551", "transmit": 126, "id": "11", "size": 0}, {"target": "199391", "color": "#0088ff", "source": "12400", "transmit": 126, "id": "12", "size": 0}, {"target": "44709", "color": "#0088ff", "source": "8551", "transmit": 126, "id": "13", "size": 0}, {"target": "12517", "color": "#0088ff", "source": "1680", "transmit": 125, "id": "14", "size": 0}, {"target": "61102", "color": "#0088ff", "source": "8551", "transmit": 125, "id": "15", "size": 0}, {"target": "16116", "color": "#0088ff", "source": "16116", "transmit": 124, "id": "16", "size": 0}, {"target": "21450", "color": "#0088ff", "source": "21450", "transmit": 124, "id": "17", "size": 0}, {"target": "21145", "color": "#0088ff", "source": "199270", "transmit": 124, "id": "18", "size": 0}, {"target": "61102", "color": "#00aaff", "source": "12400", "transmit": 123, "id": "19", "size": 0}, {"target": "25046", "color": "#00aaff", "source": "1680", "transmit": 104, "id": "20", "size": 0}, {"target": "47956", "color": "#00aaff", "source": "47956", "transmit": 67, "id": "21", "size": 0}, {"target": "200478", "color": "#00aaff", "source": "1680", "transmit": 64, "id": "22", "size": 0}, {"target": "198484", "color": "#00aaff", "source": "198484", "transmit": 63, "id": "23", "size": 0}, {"target": "15823", "color": "#00aaff", "source": "25003", "transmit": 63, "id": "24", "size": 0}, {"target": "204814", "color": "#00aaff", "source": "12400", "transmit": 63, "id": "25", "size": 0}, {"target": "199267", "color": "#00aaff", "source": "8551", "transmit": 63, "id": "26", "size": 0}, {"target": "35435", "color": "#00aaff", "source": "8551", "transmit": 63, "id": "27", "size": 0}, {"target": "56378", "color": "#00aaff", "source": "25003", "transmit": 63, "id": "28", "size": 0}, {"target": "35435", "color": "#33bbff", "source": "1680", "transmit": 63, "id": "29", "size": 0}, {"target": "206056", "color": "#33bbff", "source": "1680", "transmit": 63, "id": "30", "size": 0}, {"target": "206614", "color": "#33bbff", "source": "1680", "transmit": 63, "id": "31", "size": 0}, {"target": "206056", "color": "#33bbff", "source": "8551", "transmit": 63, "id": "32", "size": 0}, {"target": "202940", "color": "#33bbff", "source": "8551", "transmit": 63, "id": "33", "size": 0}, {"target": "201093", "color": "#33bbff", "source": "12400", "transmit": 63, "id": "34", "size": 0}, {"target": "42994", "color": "#33bbff", "source": "12400", "transmit": 62, "id": "35", "size": 0}, {"target": "43945", "color": "#33bbff", "source": "8551", "transmit": 62, "id": "36", "size": 0}, {"target": "58018", "color": "#33bbff", "source": "8551", "transmit": 62, "id": "37", "size": 0}, {"target": "31391", "color": "#33bbff", "source": "8551", "transmit": 60, "id": "38", "size": 0}, {"target": "198484", "color": "#66ccff", "source": "1680", "transmit": 53, "id": "39", "size": 0}, {"target": "199270", "color": "#66ccff", "source": "1680", "transmit": 47, "id": "40", "size": 0}, {"target": "42925", "color": "#66ccff", "source": "12400", "transmit": 38, "id": "41", "size": 0}, {"target": "200742", "color": "#66ccff", "source": "8551", "transmit": 37, "id": "42", "size": 0}, {"target": "8867", "color": "#66ccff", "source": "1680", "transmit": 37, "id": "43", "size": 0}, {"target": "8867", "color": "#66ccff", "source": "8551", "transmit": 26, "id": "44", "size": 0}, {"target": "6810", "color": "#66ccff", "source": "8551", "transmit": 16, "id": "45", "size": 0}, {"target": "47956", "color": "#66ccff", "source": "8551", "transmit": 14, "id": "46", "size": 0}, {"target": "8551", "color": "#66ccff", "source": "8551", "transmit": 9, "id": "47", "size": 0}, {"target": "61102", "color": "#66ccff", "source": "5585", "transmit": 3, "id": "48", "size": 0}]}