{"nodes": [{"size": 1.0, "y": -0.0, "name": "LCPR-HSD - Liberty Cablevision of Puerto Rico LTD", "country_code": "PR", "x": 0.0, "color": "#0055ff", "country": "\u6ce2\u591a\u9ece\u5404", "_id": "14638", "id": "14638", "label": "14638"}, {"size": 0.7161962773831755, "y": -0.8363375406822037, "name": "CENTENNIAL-PR - AT&T Mobility Puerto Rico", "country_code": "PR", "x": -1.14636527438894, "color": "#0088ff", "country": "\u6ce2\u591a\u9ece\u5404", "_id": "11992", "id": "11992", "label": "11992"}, {"size": 0.5501817420872644, "y": 2.2411464003007384, "name": "OSNET - OSNET Wireless", "country_code": "PR", "x": 0.1888767884369364, "color": "#00aaff", "country": "\u6ce2\u591a\u9ece\u5404", "_id": "21559", "id": "21559", "label": "21559"}, {"size": 0.43239255476635097, "y": 1.085289988755634, "name": "BTIL-ASN1 - Blackburn Technologies II, LLC", "country_code": "PR", "x": -2.622327389443115, "color": "#00aaff", "country": "\u6ce2\u591a\u9ece\u5404", "_id": "23379", "id": "23379", "label": "23379"}, {"size": 0.34102816302237526, "y": 0.4165583232035285, "name": "COQUI-NET - DATACOM CARIBE, INC.", "country_code": "PR", "x": -3.2684210578827657, "color": "#33bbff", "country": "\u6ce2\u591a\u9ece\u5404", "_id": "10396", "id": "10396", "label": "10396"}, {"size": 0.26637801947044004, "y": -1.1854408910637004, "name": "CRITICALHUBNET - Critical Hub Networks", "country_code": "PR", "x": 3.471276444148024, "color": "#33bbff", "country": "\u6ce2\u591a\u9ece\u5404", "_id": "23114", "id": "23114", "label": "23114"}, {"size": 0.20326222241338676, "y": -3.148506140605531, "name": "DREYFOUS - DREYFOUS & ASSOCIATES", "country_code": "PR", "x": -2.440632343965525, "color": "#33bbff", "country": "\u6ce2\u591a\u9ece\u5404", "_id": "35892", "id": "35892", "label": "35892"}, {"size": 0, "y": -4.755282581475767, "name": "AERONET-WIRELESS - Aeronet Wireless", "country_code": "PR", "x": -1.5450849718747377, "color": "#99ddff", "country": "\u6ce2\u591a\u9ece\u5404", "_id": "14979", "id": "14979", "label": "14979"}, {"size": 0, "y": -4.755282581475768, "name": "NUSTREAM-COMMUNICATIONS - Nustream Communications", "country_code": "PR", "x": 1.5450849718747361, "color": "#99ddff", "country": "\u6ce2\u591a\u9ece\u5404", "_id": "18895", "id": "18895", "label": "18895"}, {"size": 0, "y": -2.938926261462367, "name": "UNONET-CORP - UNONET CORP", "country_code": "PR", "x": 4.045084971874736, "color": "#99ddff", "country": "\u6ce2\u591a\u9ece\u5404", "_id": "14534", "id": "14534", "label": "14534"}, {"size": 0, "y": 0.0, "name": "ICENET - WorldNet Telecommunications, Inc.", "country_code": "PR", "x": 5.0, "color": "#99ddff", "country": "\u6ce2\u591a\u9ece\u5404", "_id": "11367", "id": "11367", "label": "11367"}, {"size": 0, "y": 2.938926261462366, "name": "PLAZA-LAS-AMERICAS - Plaza Las Americas, Inc.", "country_code": "PR", "x": 4.045084971874737, "color": "#99ddff", "country": "\u6ce2\u591a\u9ece\u5404", "_id": "62931", "id": "62931", "label": "62931"}, {"size": 0, "y": 4.755282581475767, "name": "SUAGM - Sistema Universitario Ana G. Mendez", "country_code": "PR", "x": 1.5450849718747373, "color": "#99ddff", "country": "\u6ce2\u591a\u9ece\u5404", "_id": "22888", "id": "22888", "label": "22888"}, {"size": 0, "y": 4.755282581475768, "name": "MSWIFIPR - M.S. Wifi Zone Inc.", "country_code": "PR", "x": -1.5450849718747368, "color": "#99ddff", "country": "\u6ce2\u591a\u9ece\u5404", "_id": "36435", "id": "36435", "label": "36435"}, {"size": 0, "y": 2.9389262614623664, "name": "PRCINTERNET-GATEWAY - PRC Internet Corp", "country_code": "PR", "x": -4.045084971874736, "color": "#99ddff", "country": "\u6ce2\u591a\u9ece\u5404", "_id": "27213", "id": "27213", "label": "27213"}, {"size": 0, "y": 6.123233995736766e-16, "name": "BOOMNETPR01 - BOOM NET", "country_code": "PR", "x": -5.0, "color": "#99ddff", "country": "\u6ce2\u591a\u9ece\u5404", "_id": "63393", "id": "63393", "label": "63393"}, {"size": 0, "y": -2.938926261462365, "name": "XAPIENS - Xapiens Corporation", "country_code": "PR", "x": -4.045084971874738, "color": "#99ddff", "country": "\u6ce2\u591a\u9ece\u5404", "_id": "30440", "id": "30440", "label": "30440"}], "edges": [{"target": "14638", "color": "#0055ff", "source": "11992", "transmit": 787, "id": "0", "size": 0}, {"target": "21559", "color": "#0055ff", "source": "14638", "transmit": 648, "id": "1", "size": 0}, {"target": "14638", "color": "#0055ff", "source": "14638", "transmit": 372, "id": "2", "size": 0}, {"target": "23379", "color": "#0055ff", "source": "23379", "transmit": 170, "id": "3", "size": 0}, {"target": "63393", "color": "#0088ff", "source": "21559", "transmit": 72, "id": "4", "size": 0}, {"target": "35892", "color": "#0088ff", "source": "14638", "transmit": 70, "id": "5", "size": 0}, {"target": "36435", "color": "#0088ff", "source": "21559", "transmit": 66, "id": "6", "size": 0}, {"target": "14534", "color": "#0088ff", "source": "21559", "transmit": 66, "id": "7", "size": 0}, {"target": "30440", "color": "#00aaff", "source": "14638", "transmit": 66, "id": "8", "size": 0}, {"target": "27213", "color": "#00aaff", "source": "11992", "transmit": 65, "id": "9", "size": 0}, {"target": "22888", "color": "#00aaff", "source": "11992", "transmit": 65, "id": "10", "size": 0}, {"target": "62931", "color": "#00aaff", "source": "14638", "transmit": 65, "id": "11", "size": 0}, {"target": "11367", "color": "#33bbff", "source": "14638", "transmit": 51, "id": "12", "size": 0}, {"target": "10396", "color": "#33bbff", "source": "10396", "transmit": 43, "id": "13", "size": 0}, {"target": "11992", "color": "#33bbff", "source": "23114", "transmit": 27, "id": "14", "size": 0}, {"target": "21559", "color": "#33bbff", "source": "11992", "transmit": 24, "id": "15", "size": 0}, {"target": "35892", "color": "#66ccff", "source": "35892", "transmit": 10, "id": "16", "size": 0}, {"target": "14979", "color": "#66ccff", "source": "21559", "transmit": 7, "id": "17", "size": 0}, {"target": "35892", "color": "#66ccff", "source": "23114", "transmit": 2, "id": "18", "size": 0}, {"target": "18895", "color": "#66ccff", "source": "11992", "transmit": 1, "id": "19", "size": 0}]}