{"nodes": [{"size": 1.0, "y": 0.0, "name": "CWSeychelles-AS", "country_code": "SC", "x": -0.0, "color": "#0055ff", "country": "\u585e\u820c\u5c14", "_id": "36958", "id": "36958", "label": "36958"}, {"size": 0.5, "y": 2.008159360225488, "name": "AirtelSeychelles", "country_code": "SC", "x": -1.4890587577187002, "color": "#00aaff", "country": "\u585e\u820c\u5c14", "_id": "37343", "id": "37343", "label": "37343"}, {"size": 0, "y": 0.0, "name": "Kokonet-BGP", "country_code": "SC", "x": 5.0, "color": "#99ddff", "country": "\u585e\u820c\u5c14", "_id": "36867", "id": "36867", "label": "36867"}], "edges": [{"target": "36958", "color": "#0088ff", "source": "36958", "transmit": 905, "id": "0", "size": 0}, {"target": "36867", "color": "#00aaff", "source": "36958", "transmit": 264, "id": "1", "size": 0}, {"target": "37343", "color": "#33bbff", "source": "37343", "transmit": 104, "id": "2", "size": 0}]}