{"nodes": [{"size": 1.0, "y": -0.0, "name": "Columbus Communications Trinidad Limited.", "country_code": "TT", "x": 0.0, "color": "#0055ff", "country": "\u7279\u7acb\u5c3c\u8fbe\u548c\u591a\u5df4\u54e5", "_id": "27665", "id": "27665", "label": "27665"}, {"size": 0, "y": 0.0, "name": "GREENDOT", "country_code": "TT", "x": 5.0, "color": "#99ddff", "country": "\u7279\u7acb\u5c3c\u8fbe\u548c\u591a\u5df4\u54e5", "_id": "27789", "id": "27789", "label": "27789"}], "edges": [{"target": "27789", "color": "#00aaff", "source": "27665", "transmit": 72, "id": "0", "size": 0}]}